df_cards/__init__.py
df_cards/apps.py
df_cards/fields.py
df_cards/models.py
df_cards/settings.py
df_cards/specs.py
django_df_cards-0.1.1.dist-info/LICENSE
django_df_cards-0.1.1.dist-info/METADATA
django_df_cards-0.1.1.dist-info/WHEEL
django_df_cards-0.1.1.dist-info/top_level.txt
django_df_cards-0.1.1.dist-info/RECORD
